setup.py
lgtm/__init__.py
lgtm/console.py
lgtm/git.py
lgtm/owners.py
lgtm/utils.py
lgtm.egg-info/PKG-INFO
lgtm.egg-info/SOURCES.txt
lgtm.egg-info/dependency_links.txt
lgtm.egg-info/entry_points.txt
lgtm.egg-info/requires.txt
lgtm.egg-info/top_level.txt
lgtm/integrations/__init__.py
lgtm/integrations/base.py
lgtm/integrations/jenkins.py
lgtm/integrations/travis.py
lgtm/tests/__init__.py
lgtm/tests/base.py
lgtm/tests/mock_github.py
lgtm/tests/test_console.py
lgtm/tests/test_git.py
lgtm/tests/test_integration_base.py
lgtm/tests/test_jenkins.py
lgtm/tests/test_owners.py
lgtm/tests/test_pull_request_ready_to_merge.py